[{"date": "2022-06-30", "count": 1}, {"date": "2022-07-31", "count": 8}, {"date": "2022-09-30", "count": 9}, {"date": "2022-10-31", "count": 19}, {"date": "2022-11-30", "count": 82}, {"date": "2022-12-31", "count": 104}, {"date": "2023-01-31", "count": 151}, {"date": "2023-02-28", "count": 241}, {"date": "2023-03-31", "count": 323}, {"date": "2023-04-30", "count": 390}, {"date": "2023-05-31", "count": 495}, {"date": "2023-06-30", "count": 964}, {"date": "2023-07-31", "count": 1561}, {"date": "2023-08-31", "count": 2125}, {"date": "2023-09-30", "count": 3128}, {"date": "2023-10-31", "count": 3890}, {"date": "2023-11-30", "count": 4535}, {"date": "2023-12-31", "count": 4952}, {"date": "2024-01-31", "count": 5416}, {"date": "2024-02-29", "count": 5800}, {"date": "2024-03-31", "count": 6148}, {"date": "2024-04-30", "count": 6382}, {"date": "2024-05-31", "count": 6635}, {"date": "2024-06-30", "count": 6790}, {"date": "2024-07-31", "count": 6921}, {"date": "2024-08-31", "count": 6992}, {"date": "2024-09-30", "count": 7124}, {"date": "2024-10-31", "count": 7389}, {"date": "2024-11-30", "count": 7525}, {"date": "2024-12-31", "count": 7659}, {"date": "2025-01-31", "count": 7784}, {"date": "2025-02-28", "count": 7898}, {"date": "2025-03-31", "count": 8035}, {"date": "2025-04-30", "count": 8134}, {"date": "2025-05-31", "count": 8277}, {"date": "2025-06-30", "count": 8384}, {"date": "2025-07-31", "count": 8502}]