[{"name": "Totale enti", "totalCount": 7658, "lastMonthCount": 150.0, "variation": 1.9}, {"name": "Enti privati", "totalCount": 132, "lastMonthCount": 3.0, "variation": 2.3}, {"name": "Enti pubblici", "totalCount": 7526, "lastMonthCount": 147.0, "variation": 1.9}, {"name": "Altri enti pubblici", "totalCount": 713, "lastMonthCount": 52.0, "variation": 55.4}, {"name": "Comuni", "totalCount": 6642, "lastMonthCount": 87.0, "variation": 1.3}, {"name": "Regioni e Province Autonome", "totalCount": 21, "lastMonthCount": 0.0, "variation": 0.0}, {"name": "Università e AFAM", "totalCount": 150, "lastMonthCount": 8.0, "variation": 5.6}]