[{"name": "Totale enti", "totalCount": 9156, "lastMonthCount": 161, "variation": 1.8}, {"name": "Enti privati", "totalCount": 193, "lastMonthCount": 15, "variation": 8.4}, {"name": "Enti pubblici", "totalCount": 8963, "lastMonthCount": 146, "variation": 1.5}, {"name": "Comuni", "totalCount": 7557, "lastMonthCount": 83, "variation": 1.0}, {"name": "Università e AFAM", "totalCount": 168, "lastMonthCount": 0, "variation": 0.0}, {"name": "Altri enti pubblici", "totalCount": 1217, "lastMonthCount": 62, "variation": 37.5}, {"name": "Regioni e Province Autonome", "totalCount": 21, "lastMonthCount": 1, "variation": 0.0}]