[{"name": "Totale enti", "totalCount": 6939, "lastMonthCount": 139.0, "variation": 1.9}, {"name": "Enti privati", "totalCount": 118, "lastMonthCount": 4.0, "variation": 3.5}, {"name": "Enti pubblici", "totalCount": 6821, "lastMonthCount": 135.0, "variation": 1.9}, {"name": "Altri enti pubblici", "totalCount": 468, "lastMonthCount": 25.0, "variation": 56.1}, {"name": "Comuni", "totalCount": 6252, "lastMonthCount": 103.0, "variation": 1.6}, {"name": "Regioni e Province Autonome", "totalCount": 20, "lastMonthCount": 0.0, "variation": 0.0}, {"name": "Università e AFAM", "totalCount": 81, "lastMonthCount": 7.0, "variation": 9.5}]